Ossarth/__init__.py
Ossarth/tool_manager.py
Ossarth/templates/__init__.py
Ossarth/templates/general_template.py
Ossarth-0.1.1.dist-info/LICENSE
Ossarth-0.1.1.dist-info/METADATA
Ossarth-0.1.1.dist-info/WHEEL
Ossarth-0.1.1.dist-info/top_level.txt
Ossarth-0.1.1.dist-info/RECORD
