Metadata-Version: 2.1
Name: Ossarth
Version: 0.1.1
Summary: A customizable Ossarth AI-powered open-source operating system toolkit
Home-page: https://github.com/Siddharth-magesh/Ossarth
Author: Siddharth Magesh
Author-email: siddharthmagesh007@gmail.com
Classifier: Programming Language :: Python :: 3
Classifier: License :: OSI Approved :: MIT License
Classifier: Operating System :: OS Independent
Requires-Python: >=3.10
License-File: LICENSE
Requires-Dist: numpy
Requires-Dist: flask
